torch_scaler/__init__.py
torch_scaler/standard_scaler.py
torch_scaler-0.0.2.dist-info/LICENSE
torch_scaler-0.0.2.dist-info/METADATA
torch_scaler-0.0.2.dist-info/WHEEL
torch_scaler-0.0.2.dist-info/top_level.txt
torch_scaler-0.0.2.dist-info/RECORD
